{
  "$schema": "https://vega.github.io/schema/vega-lite/v5.json",
  "data": {
    "name": "query_result",
    "values": [
      {
        "percentage": 18,
        "academic_title": "Unknown",
        "professor_count": 9
      },
      {
        "percentage": 14,
        "academic_title": "Prof. dr hab. inż.",
        "professor_count": 7
      },
      {
        "percentage": 14,
        "academic_title": "Prof. nadzw. dr hab. inż.",
        "professor_count": 7
      },
      {
        "percentage": 10,
        "academic_title": "Dr inż.",
        "professor_count": 5
      },
      {
        "percentage": 8,
        "academic_title": "Dr hab. inż.",
        "professor_count": 4
      },
      {
        "percentage": 8,
        "academic_title": "Inż.",
        "professor_count": 4
      },
      {
        "percentage": 8,
        "academic_title": "Prof. zw. dr hab. inż.",
        "professor_count": 4
      },
      {
        "percentage": 6,
        "academic_title": "Mgr inż.",
        "professor_count": 3
      },
      {
        "percentage": 6,
        "academic_title": "Prof. dr inż.",
        "professor_count": 3
      },
      {
        "percentage": 4,
        "academic_title": "Dr hab.",
        "professor_count": 2
      },
      {
        "percentage": 2,
        "academic_title": "Dr",
        "professor_count": 1
      },
      {
        "percentage": 2,
        "academic_title": "Prof. dr hab.",
        "professor_count": 1
      }
    ]
  },
  "title": "Distribution of academic titles among professors",
  "mark": {
    "type": "bar",
    "cornerRadius": 3
  },
  "encoding": {
    "y": {
      "field": "academic_title",
      "type": "nominal",
      "title": "Academic title",
      "sort": {
        "field": "professor_count",
        "order": "descending"
      }
    },
    "x": {
      "field": "professor_count",
      "type": "quantitative",
      "title": "Number of professors"
    },
    "color": {
      "field": "percentage",
      "type": "quantitative",
      "title": "Share (%)",
      "scale": {
        "scheme": "blues"
      }
    },
    "tooltip": [
      {
        "field": "academic_title",
        "type": "nominal",
        "title": "Academic title"
      },
      {
        "field": "professor_count",
        "type": "quantitative",
        "title": "Professor count"
      },
      {
        "field": "percentage",
        "type": "quantitative",
        "title": "Percentage",
        "format": ".2f"
      }
    ]
  },
  "width": 640,
  "height": {
    "step": 24
  },
  "datasets": {
    "query_result": [
      {
        "percentage": 18,
        "academic_title": "Unknown",
        "professor_count": 9
      },
      {
        "percentage": 14,
        "academic_title": "Prof. dr hab. inż.",
        "professor_count": 7
      },
      {
        "percentage": 14,
        "academic_title": "Prof. nadzw. dr hab. inż.",
        "professor_count": 7
      },
      {
        "percentage": 10,
        "academic_title": "Dr inż.",
        "professor_count": 5
      },
      {
        "percentage": 8,
        "academic_title": "Dr hab. inż.",
        "professor_count": 4
      },
      {
        "percentage": 8,
        "academic_title": "Inż.",
        "professor_count": 4
      },
      {
        "percentage": 8,
        "academic_title": "Prof. zw. dr hab. inż.",
        "professor_count": 4
      },
      {
        "percentage": 6,
        "academic_title": "Mgr inż.",
        "professor_count": 3
      },
      {
        "percentage": 6,
        "academic_title": "Prof. dr inż.",
        "professor_count": 3
      },
      {
        "percentage": 4,
        "academic_title": "Dr hab.",
        "professor_count": 2
      },
      {
        "percentage": 2,
        "academic_title": "Dr",
        "professor_count": 1
      },
      {
        "percentage": 2,
        "academic_title": "Prof. dr hab.",
        "professor_count": 1
      }
    ]
  }
}
